datasette_mask_columns/__init__.py
datasette_mask_columns-0.2.2.dist-info/LICENSE
datasette_mask_columns-0.2.2.dist-info/METADATA
datasette_mask_columns-0.2.2.dist-info/WHEEL
datasette_mask_columns-0.2.2.dist-info/entry_points.txt
datasette_mask_columns-0.2.2.dist-info/top_level.txt
datasette_mask_columns-0.2.2.dist-info/RECORD
