Metadata-Version: 2.1
Name: datasette-mask-columns
Version: 0.2.2
Summary: Datasette plugin that masks specified database columns
Home-page: https://github.com/simonw/datasette-mask-columns
Author: Simon Willison
License: Apache License, Version 2.0
License-File: LICENSE
Requires-Dist: datasette
Provides-Extra: test
Requires-Dist: pytest ; extra == 'test'
Requires-Dist: pytest-asyncio ; extra == 'test'
Requires-Dist: httpx ; extra == 'test'
Requires-Dist: sqlite-utils ; extra == 'test'
